[
  {
    "title": "娛樂已發佈示例貼文 2026-03-09 #1",
    "category": "娛樂",
    "thumbnail": "data/samples/Dummy1.png",
    "Post URL": "https://example.com/published?id=500001",
    "publish_time": "2026-03-09T08:00:00Z",
    "popular_count": 1
  },
  {
    "title": "娛樂已發佈示例貼文 2026-03-09 #2",
    "category": "娛樂",
    "thumbnail": "data/samples/Dummy1.png",
    "Post URL": "https://example.com/published?id=500002",
    "publish_time": "2026-03-09T12:11:00Z",
    "popular_count": 2
  },
  {
    "title": "娛樂已發佈示例貼文 2026-03-09 #3",
    "category": "娛樂",
    "thumbnail": "data/samples/Dummy1.png",
    "Post URL": "https://example.com/published?id=500003",
    "publish_time": "2026-03-09T16:22:00Z",
    "popular_count": 3
  },
  {
    "title": "社會事已發佈示例貼文 2026-03-09 #1",
    "category": "社會事",
    "thumbnail": "data/samples/Dummy1.png",
    "Post URL": "https://example.com/published?id=500004",
    "publish_time": "2026-03-09T10:07:00Z",
    "popular_count": 2
  },
  {
    "title": "社會事已發佈示例貼文 2026-03-09 #2",
    "category": "社會事",
    "thumbnail": "data/samples/Dummy1.png",
    "Post URL": "https://example.com/published?id=500005",
    "publish_time": "2026-03-09T14:18:00Z",
    "popular_count": 3
  },
  {
    "title": "社會事已發佈示例貼文 2026-03-09 #3",
    "category": "社會事",
    "thumbnail": "data/samples/Dummy1.png",
    "Post URL": "https://example.com/published?id=500006",
    "publish_time": "2026-03-09T18:29:00Z",
    "popular_count": 4
  },
  {
    "title": "大視野已發佈示例貼文 2026-03-09 #1",
    "category": "大視野",
    "thumbnail": "data/samples/Dummy1.png",
    "Post URL": "https://example.com/published?id=500007",
    "publish_time": "2026-03-09T12:14:00Z",
    "popular_count": 3
  },
  {
    "title": "大視野已發佈示例貼文 2026-03-09 #2",
    "category": "大視野",
    "thumbnail": "data/samples/Dummy1.png",
    "Post URL": "https://example.com/published?id=500008",
    "publish_time": "2026-03-09T16:25:00Z",
    "popular_count": 4
  },
  {
    "title": "大視野已發佈示例貼文 2026-03-09 #3",
    "category": "大視野",
    "thumbnail": "data/samples/Dummy1.png",
    "Post URL": "https://example.com/published?id=500009",
    "publish_time": "2026-03-09T20:36:00Z",
    "popular_count": 1
  },
  {
    "title": "兩岸已發佈示例貼文 2026-03-09 #1",
    "category": "兩岸",
    "thumbnail": "data/samples/Dummy1.png",
    "Post URL": "https://example.com/published?id=500010",
    "publish_time": "2026-03-09T14:21:00Z",
    "popular_count": 4
  },
  {
    "title": "兩岸已發佈示例貼文 2026-03-09 #2",
    "category": "兩岸",
    "thumbnail": "data/samples/Dummy1.png",
    "Post URL": "https://example.com/published?id=500011",
    "publish_time": "2026-03-09T18:32:00Z",
    "popular_count": 1
  },
  {
    "title": "兩岸已發佈示例貼文 2026-03-09 #3",
    "category": "兩岸",
    "thumbnail": "data/samples/Dummy1.png",
    "Post URL": "https://example.com/published?id=500012",
    "publish_time": "2026-03-09T22:43:00Z",
    "popular_count": 2
  },
  {
    "title": "法庭事已發佈示例貼文 2026-03-09 #1",
    "category": "法庭事",
    "thumbnail": "data/samples/Dummy1.png",
    "Post URL": "https://example.com/published?id=500013",
    "publish_time": "2026-03-09T16:28:00Z",
    "popular_count": 1
  },
  {
    "title": "法庭事已發佈示例貼文 2026-03-09 #2",
    "category": "法庭事",
    "thumbnail": "data/samples/Dummy1.png",
    "Post URL": "https://example.com/published?id=500014",
    "publish_time": "2026-03-09T20:39:00Z",
    "popular_count": 2
  },
  {
    "title": "法庭事已發佈示例貼文 2026-03-09 #3",
    "category": "法庭事",
    "thumbnail": "data/samples/Dummy1.png",
    "Post URL": "https://example.com/published?id=500015",
    "publish_time": "2026-03-09T00:50:00Z",
    "popular_count": 3
  },
  {
    "title": "消費已發佈示例貼文 2026-03-09 #1",
    "category": "消費",
    "thumbnail": "data/samples/Dummy1.png",
    "Post URL": "https://example.com/published?id=500016",
    "publish_time": "2026-03-09T18:35:00Z",
    "popular_count": 2
  },
  {
    "title": "消費已發佈示例貼文 2026-03-09 #2",
    "category": "消費",
    "thumbnail": "data/samples/Dummy1.png",
    "Post URL": "https://example.com/published?id=500017",
    "publish_time": "2026-03-09T22:46:00Z",
    "popular_count": 3
  },
  {
    "title": "消費已發佈示例貼文 2026-03-09 #3",
    "category": "消費",
    "thumbnail": "data/samples/Dummy1.png",
    "Post URL": "https://example.com/published?id=500018",
    "publish_time": "2026-03-09T02:57:00Z",
    "popular_count": 4
  },
  {
    "title": "心韓已發佈示例貼文 2026-03-09 #1",
    "category": "心韓",
    "thumbnail": "data/samples/Dummy1.png",
    "Post URL": "https://example.com/published?id=500019",
    "publish_time": "2026-03-09T20:42:00Z",
    "popular_count": 3
  },
  {
    "title": "心韓已發佈示例貼文 2026-03-09 #2",
    "category": "心韓",
    "thumbnail": "data/samples/Dummy1.png",
    "Post URL": "https://example.com/published?id=500020",
    "publish_time": "2026-03-09T00:53:00Z",
    "popular_count": 4
  },
  {
    "title": "心韓已發佈示例貼文 2026-03-09 #3",
    "category": "心韓",
    "thumbnail": "data/samples/Dummy1.png",
    "Post URL": "https://example.com/published?id=500021",
    "publish_time": "2026-03-09T04:04:00Z",
    "popular_count": 1
  },
  {
    "title": "娛樂已發佈示例貼文 2026-03-10 #1",
    "category": "娛樂",
    "thumbnail": "data/samples/Dummy1.png",
    "Post URL": "https://example.com/published?id=500022",
    "publish_time": "2026-03-10T08:00:00Z",
    "popular_count": 1
  },
  {
    "title": "娛樂已發佈示例貼文 2026-03-10 #2",
    "category": "娛樂",
    "thumbnail": "data/samples/Dummy1.png",
    "Post URL": "https://example.com/published?id=500023",
    "publish_time": "2026-03-10T12:11:00Z",
    "popular_count": 2
  },
  {
    "title": "娛樂已發佈示例貼文 2026-03-10 #3",
    "category": "娛樂",
    "thumbnail": "data/samples/Dummy1.png",
    "Post URL": "https://example.com/published?id=500024",
    "publish_time": "2026-03-10T16:22:00Z",
    "popular_count": 3
  },
  {
    "title": "社會事已發佈示例貼文 2026-03-10 #1",
    "category": "社會事",
    "thumbnail": "data/samples/Dummy1.png",
    "Post URL": "https://example.com/published?id=500025",
    "publish_time": "2026-03-10T10:07:00Z",
    "popular_count": 2
  },
  {
    "title": "社會事已發佈示例貼文 2026-03-10 #2",
    "category": "社會事",
    "thumbnail": "data/samples/Dummy1.png",
    "Post URL": "https://example.com/published?id=500026",
    "publish_time": "2026-03-10T14:18:00Z",
    "popular_count": 3
  },
  {
    "title": "社會事已發佈示例貼文 2026-03-10 #3",
    "category": "社會事",
    "thumbnail": "data/samples/Dummy1.png",
    "Post URL": "https://example.com/published?id=500027",
    "publish_time": "2026-03-10T18:29:00Z",
    "popular_count": 4
  },
  {
    "title": "大視野已發佈示例貼文 2026-03-10 #1",
    "category": "大視野",
    "thumbnail": "data/samples/Dummy1.png",
    "Post URL": "https://example.com/published?id=500028",
    "publish_time": "2026-03-10T12:14:00Z",
    "popular_count": 3
  },
  {
    "title": "大視野已發佈示例貼文 2026-03-10 #2",
    "category": "大視野",
    "thumbnail": "data/samples/Dummy1.png",
    "Post URL": "https://example.com/published?id=500029",
    "publish_time": "2026-03-10T16:25:00Z",
    "popular_count": 4
  },
  {
    "title": "大視野已發佈示例貼文 2026-03-10 #3",
    "category": "大視野",
    "thumbnail": "data/samples/Dummy1.png",
    "Post URL": "https://example.com/published?id=500030",
    "publish_time": "2026-03-10T20:36:00Z",
    "popular_count": 1
  },
  {
    "title": "兩岸已發佈示例貼文 2026-03-10 #1",
    "category": "兩岸",
    "thumbnail": "data/samples/Dummy1.png",
    "Post URL": "https://example.com/published?id=500031",
    "publish_time": "2026-03-10T14:21:00Z",
    "popular_count": 4
  },
  {
    "title": "兩岸已發佈示例貼文 2026-03-10 #2",
    "category": "兩岸",
    "thumbnail": "data/samples/Dummy1.png",
    "Post URL": "https://example.com/published?id=500032",
    "publish_time": "2026-03-10T18:32:00Z",
    "popular_count": 1
  },
  {
    "title": "兩岸已發佈示例貼文 2026-03-10 #3",
    "category": "兩岸",
    "thumbnail": "data/samples/Dummy1.png",
    "Post URL": "https://example.com/published?id=500033",
    "publish_time": "2026-03-10T22:43:00Z",
    "popular_count": 2
  },
  {
    "title": "法庭事已發佈示例貼文 2026-03-10 #1",
    "category": "法庭事",
    "thumbnail": "data/samples/Dummy1.png",
    "Post URL": "https://example.com/published?id=500034",
    "publish_time": "2026-03-10T16:28:00Z",
    "popular_count": 1
  },
  {
    "title": "法庭事已發佈示例貼文 2026-03-10 #2",
    "category": "法庭事",
    "thumbnail": "data/samples/Dummy1.png",
    "Post URL": "https://example.com/published?id=500035",
    "publish_time": "2026-03-10T20:39:00Z",
    "popular_count": 2
  },
  {
    "title": "法庭事已發佈示例貼文 2026-03-10 #3",
    "category": "法庭事",
    "thumbnail": "data/samples/Dummy1.png",
    "Post URL": "https://example.com/published?id=500036",
    "publish_time": "2026-03-10T00:50:00Z",
    "popular_count": 3
  },
  {
    "title": "消費已發佈示例貼文 2026-03-10 #1",
    "category": "消費",
    "thumbnail": "data/samples/Dummy1.png",
    "Post URL": "https://example.com/published?id=500037",
    "publish_time": "2026-03-10T18:35:00Z",
    "popular_count": 2
  },
  {
    "title": "消費已發佈示例貼文 2026-03-10 #2",
    "category": "消費",
    "thumbnail": "data/samples/Dummy1.png",
    "Post URL": "https://example.com/published?id=500038",
    "publish_time": "2026-03-10T22:46:00Z",
    "popular_count": 3
  },
  {
    "title": "消費已發佈示例貼文 2026-03-10 #3",
    "category": "消費",
    "thumbnail": "data/samples/Dummy1.png",
    "Post URL": "https://example.com/published?id=500039",
    "publish_time": "2026-03-10T02:57:00Z",
    "popular_count": 4
  },
  {
    "title": "心韓已發佈示例貼文 2026-03-10 #1",
    "category": "心韓",
    "thumbnail": "data/samples/Dummy1.png",
    "Post URL": "https://example.com/published?id=500040",
    "publish_time": "2026-03-10T20:42:00Z",
    "popular_count": 3
  },
  {
    "title": "心韓已發佈示例貼文 2026-03-10 #2",
    "category": "心韓",
    "thumbnail": "data/samples/Dummy1.png",
    "Post URL": "https://example.com/published?id=500041",
    "publish_time": "2026-03-10T00:53:00Z",
    "popular_count": 4
  },
  {
    "title": "心韓已發佈示例貼文 2026-03-10 #3",
    "category": "心韓",
    "thumbnail": "data/samples/Dummy1.png",
    "Post URL": "https://example.com/published?id=500042",
    "publish_time": "2026-03-10T04:04:00Z",
    "popular_count": 1
  }
]